slurry/__init__.py
slurry/_pipeline.py
slurry/_tap.py
slurry/environments/__init__.py
slurry/environments/_multiprocessing.py
slurry/environments/_threading.py
slurry/environments/_trio.py
slurry/sections/__init__.py
slurry/sections/_buffers.py
slurry/sections/_combiners.py
slurry/sections/_filters.py
slurry/sections/_producers.py
slurry/sections/_refiners.py
slurry/sections/abc.py
slurry/sections/weld.py
slurry-1.3.1.dist-info/LICENSE
slurry-1.3.1.dist-info/WHEEL
slurry-1.3.1.dist-info/METADATA
slurry-1.3.1.dist-info/RECORD
