Metadata-Version: 2.1
Name: slurry
Version: 1.3.1
Summary: An async stream processing microframework
Home-page: https://github.com/andersea/slurry
License: MIT
Keywords: async,iteration,generators,stream,processing,trio
Author: Anders Ellenshøj Andersen
Author-email: andersa@ellenshoej.dk
Requires-Python: >=3.8,<4.0
Classifier: Development Status :: 5 - Production/Stable
Classifier: Framework :: Trio
Classifier: Intended Audience :: Developers
Classifier: License :: OSI Approved :: MIT License
Classifier: Natural Language :: English
Classifier: Programming Language :: Python :: 3
Classifier: Programming Language :: Python :: 3.10
Classifier: Programming Language :: Python :: 3.8
Classifier: Programming Language :: Python :: 3.9
Requires-Dist: trio (>=0.21.0,<0.22.0)
